LICENSE.txt
MANIFEST.in
README.md
setup.py
cython/hyperfunc.cpp
cython/hyperfunc.pyx
cython/hyperfunc_save.pyx
hyperclip/__init__.py
hyperclip/hyperclip.py
hyperclip/hyperplane.py
hyperclip.egg-info/PKG-INFO
hyperclip.egg-info/SOURCES.txt
hyperclip.egg-info/dependency_links.txt
hyperclip.egg-info/requires.txt
hyperclip.egg-info/top_level.txt
tests/test.py
tests/test_2d_plot.py